odoo/addons/event_registration_mass_mailing/README.rst
odoo/addons/event_registration_mass_mailing/__init__.py
odoo/addons/event_registration_mass_mailing/__manifest__.py
odoo/addons/event_registration_mass_mailing/i18n/es.po
odoo/addons/event_registration_mass_mailing/models/__init__.py
odoo/addons/event_registration_mass_mailing/models/event_registration.py
odoo/addons/event_registration_mass_mailing/readme/CONTRIBUTORS.rst
odoo/addons/event_registration_mass_mailing/readme/DESCRIPTION.rst
odoo/addons/event_registration_mass_mailing/readme/USAGE.rst
odoo/addons/event_registration_mass_mailing/tests/__init__.py
odoo/addons/event_registration_mass_mailing/tests/test_event_registration_mail_list_wizard.py
odoo/addons/event_registration_mass_mailing/views/event_registration.xml
odoo/addons/event_registration_mass_mailing/wizard/__init__.py
odoo/addons/event_registration_mass_mailing/wizard/event_registration_mail_list_wizard.py
odoo/addons/event_registration_mass_mailing/wizard/event_registration_mail_list_wizard.xml
odoo11_addon_event_registration_mass_mailing-11.0.1.0.1.dist-info/METADATA
odoo11_addon_event_registration_mass_mailing-11.0.1.0.1.dist-info/RECORD
odoo11_addon_event_registration_mass_mailing-11.0.1.0.1.dist-info/WHEEL
odoo11_addon_event_registration_mass_mailing-11.0.1.0.1.dist-info/top_level.txt
